tooload/__init__.py
tooload/_config.py
tooload/_load.py
tooload/error.py
tooload-0.0.2.dist-info/LICENSE.md
tooload-0.0.2.dist-info/METADATA
tooload-0.0.2.dist-info/WHEEL
tooload-0.0.2.dist-info/top_level.txt
tooload-0.0.2.dist-info/RECORD
