Metadata-Version: 2.2
Name: tooload
Version: 0.0.2
Summary: One-line loading tools config (pyproject.toml and tool specific)
Author: nosludge
Maintainer: nosludge
License: Apache License
Project-URL: Changelog, https://github.com/nosludge/tooload/blob/master/CHANGELOG.md
Project-URL: Documentation, https://nosludge.github.io/tooload
Project-URL: Homepage, https://nosludge.github.io/tooload
Project-URL: Issues, https://github.com/nosludge/tooload/issues
Project-URL: Repository, https://github.com/nosludge/tooload
Classifier: Development Status :: 2 - Pre-Alpha
Classifier: Intended Audience :: Developers
Classifier: License :: OSI Approved :: Apache Software License
Classifier: Programming Language :: Python
Classifier: Programming Language :: Python :: 3 :: Only
Classifier: Programming Language :: Python :: 3.11
Classifier: Programming Language :: Python :: 3.12
Classifier: Programming Language :: Python :: 3.13
Classifier: Topic :: Software Development :: Libraries
Classifier: Topic :: Software Development :: Libraries :: Python Modules
Classifier: Typing :: Typed
Requires-Python: >=3.11
License-File: LICENSE.md
